{
	"animations": [
		{
			"offsets": [
				210,
				31
			],
			"fps": 24,
			"anim": "Right miss",
			"loop": false,
			"name": "singRIGHTmiss"
		},
		{
			"offsets": [
				32,
				43
			],
			"fps": 24,
			"anim": "CEDAR DOWN",
			"loop": false,
			"name": "singDOWN"
		},
		{
			"offsets": [
				2,
				92
			],
			"fps": 24,
			"anim": "FROWN",
			"loop": false,
			"name": "idle-frown"
		},
		{
			"offsets": [
				100,
				2
			],
			"fps": 24,
			"anim": "left miss",
			"loop": false,
			"name": "singLEFTmiss"
		},
		{
			"offsets": [
				15,
				107
			],
			"fps": 24,
			"anim": "CEDAR UP",
			"loop": false,
			"name": "singUP"
		},
		{
			"offsets": [
				63,
				101
			],
			"fps": 24,
			"anim": "CEDAR HEY",
			"loop": false,
			"name": "hey"
		},
		{
			"offsets": [
				6,
				93
			],
			"fps": 24,
			"anim": "CEDAR IDLE",
			"loop": false,
			"name": "idle"
		},
		{
			"offsets": [
				52,
				-270
			],
			"fps": 24,
			"anim": "DOWN MISS",
			"loop": false,
			"name": "singDOWNmiss"
		},
		{
			"offsets": [
				-20,
				102
			],
			"fps": 24,
			"anim": "CEDAR RIGHT",
			"loop": false,
			"name": "singRIGHT"
		},
		{
			"offsets": [
				93,
				78
			],
			"fps": 24,
			"anim": "CEDAR LEFT",
			"loop": false,
			"name": "singLEFT"
		},
		{
			"offsets": [
				6,
				63
			],
			"fps": 24,
			"anim": "UP MISS (FNFever)",
			"loop": false,
			"name": "singUPmiss"
		},
		{
			"offsets": [
				31,
				110
			],
			"fps": 24,
			"anim": "CEDAR DODGE",
			"loop": false,
			"name": "dodge"
		}
	],
	"noAntialiasing": false,
	"isDeathAnim": false,
	"facingLeft": true,
	"file": "fever/CedarHD",
	"color": "C353E3"
}