{
	"animations": [
		{
			"offsets": [
				0,
				70
			],
			"fps": 24,
			"anim": "alt idle",
			"loop": false,
			"name": "idle-frown"
		},
		{
			"offsets": [
				55,
				5
			],
			"fps": 24,
			"anim": "down0",
			"loop": false,
			"name": "singDOWN"
		},
		{
			"offsets": [
				10,
				79
			],
			"fps": 24,
			"anim": "right miss",
			"loop": false,
			"name": "singRIGHTmiss"
		},
		{
			"offsets": [
				-43,
				119
			],
			"fps": 24,
			"anim": "left miss",
			"loop": false,
			"name": "singLEFTmiss"
		},
		{
			"offsets": [
				-11,
				102
			],
			"fps": 24,
			"anim": "up0",
			"loop": false,
			"name": "singUP"
		},
		{
			"offsets": [
				-18,
				80
			],
			"fps": 24,
			"anim": "hey",
			"loop": false,
			"name": "hey"
		},
		{
			"offsets": [
				0,
				70
			],
			"fps": 24,
			"anim": "idle",
			"loop": false,
			"name": "idle"
		},
		{
			"offsets": [
				-22,
				70
			],
			"fps": 24,
			"anim": "right0",
			"loop": false,
			"name": "singRIGHT"
		},
		{
			"offsets": [
				57,
				0
			],
			"fps": 24,
			"anim": "down miss",
			"loop": false,
			"name": "singDOWNmiss"
		},
		{
			"offsets": [
				-50,
				119
			],
			"fps": 24,
			"anim": "left0",
			"loop": false,
			"name": "singLEFT"
		},
		{
			"offsets": [
				-10,
				69
			],
			"fps": 24,
			"anim": "up miss",
			"loop": false,
			"name": "singUPmiss"
		},
		{
			"offsets": [
				-51,
				129
			],
			"fps": 24,
			"anim": "dodge",
			"loop": false,
			"name": "dodge"
		}
	],
	"noAntialiasing": false,
	"isDeathAnim": false,
	"facingLeft": true,
	"file": "costumes/teasar",
	"color": "C353E3"
}